python_mmdt-0.3.1.data/purelib/python_mmdt/__init__.py
python_mmdt-0.3.1.data/purelib/python_mmdt/mmdt/__init__.py
python_mmdt-0.3.1.data/purelib/python_mmdt/mmdt/common.py
python_mmdt-0.3.1.data/purelib/python_mmdt/mmdt/feature.py
python_mmdt-0.3.1.data/purelib/python_mmdt/mmdt/libcore.dll
python_mmdt-0.3.1.data/purelib/python_mmdt/mmdt/mmdt.py
python_mmdt-0.3.1.data/purelib/python_mmdt/mmdt/mmdt_feature.data
python_mmdt-0.3.1.data/purelib/python_mmdt/mmdt/run.py
python_mmdt-0.3.1.data/purelib/python_mmdt/mmdt/serialized.py
python_mmdt-0.3.1.data/purelib/tests/tools/__init__.py
python_mmdt-0.3.1.data/purelib/tests/tools/build_feature.py
python_mmdt-0.3.1.data/purelib/tests/tools/process_feature.py
python_mmdt-0.3.1.dist-info/LICENSE
python_mmdt-0.3.1.dist-info/METADATA
python_mmdt-0.3.1.dist-info/WHEEL
python_mmdt-0.3.1.dist-info/entry_points.txt
python_mmdt-0.3.1.dist-info/top_level.txt
python_mmdt-0.3.1.dist-info/RECORD
