Metadata-Version: 2.1
Name: python-mmdt
Version: 0.3.1
Summary: Python wrapper for the mmdt library
Home-page: https://github.com/a232319779/python_mmdt
Author: ddvv
Author-email: dadavivi512@gmail.com
License: MIT
Keywords: mmdt
Platform: UNKNOWN
Classifier: License :: OSI Approved :: MIT License
Classifier: Operating System :: OS Independent
Classifier: Programming Language :: Python
Classifier: Programming Language :: Python :: 3.6
Classifier: Programming Language :: Python :: 3.7
Classifier: Programming Language :: Python :: 3.8
Classifier: Programming Language :: Python :: 3.9
Classifier: Programming Language :: Python :: Implementation :: PyPy
Classifier: Topic :: Software Development :: Libraries :: Python Modules
Requires-Python: >=3.6
License-File: LICENSE
Requires-Dist: requests
Requires-Dist: numpy
